DyldExtractor/__init__.py
DyldExtractor/cache_context.py
DyldExtractor/extraction_context.py
DyldExtractor/file_context.py
DyldExtractor/leb128.py
DyldExtractor/structure.py
DyldExtractor/converter/__init__.py
DyldExtractor/converter/chained_fixups.py
DyldExtractor/converter/linkedit_optimizer.py
DyldExtractor/converter/macho_offset.py
DyldExtractor/converter/objc_fixer.py
DyldExtractor/converter/slide_info.py
DyldExtractor/converter/stub_fixer.py
DyldExtractor/dyld/__init__.py
DyldExtractor/dyld/dyld_constants.py
DyldExtractor/dyld/dyld_context.py
DyldExtractor/dyld/dyld_structs.py
DyldExtractor/dyld/dyld_trie.py
DyldExtractor/kc/__init__.py
DyldExtractor/kc/kc_context.py
DyldExtractor/macho/__init__.py
DyldExtractor/macho/fixup_chains_structs.py
DyldExtractor/macho/macho_constants.py
DyldExtractor/macho/macho_context.py
DyldExtractor/macho/macho_structs.py
DyldExtractor/macho/segment_context.py
DyldExtractor/objc/__init__.py
DyldExtractor/objc/objc_structs.py
dyldextractor-2.2.2.data/scripts/dyldex
dyldextractor-2.2.2.data/scripts/dyldex_all
dyldextractor-2.2.2.data/scripts/kextex
dyldextractor-2.2.2.data/scripts/kextex_all
dyldextractor-2.2.2.dist-info/LICENSE
dyldextractor-2.2.2.dist-info/METADATA
dyldextractor-2.2.2.dist-info/WHEEL
dyldextractor-2.2.2.dist-info/top_level.txt
dyldextractor-2.2.2.dist-info/RECORD
